django_error_logger-1.0.1.dist-info/licenses/LICENSE
error_logger/__init__.py
error_logger/admin.py
error_logger/apps.py
error_logger/forms.py
error_logger/middleware.py
error_logger/models.py
error_logger/setup.py
error_logger/urls.py
error_logger/verify_package.py
error_logger/views.py
error_logger/migrations/0001_initial.py
error_logger/migrations/__init__.py
error_logger/templates/error_logger/test_large_post_error.html
error_logger/templates/error_logger/test_post_error.html
django_error_logger-1.0.1.dist-info/METADATA
django_error_logger-1.0.1.dist-info/WHEEL
django_error_logger-1.0.1.dist-info/top_level.txt
django_error_logger-1.0.1.dist-info/RECORD
