Metadata-Version: 2.4
Name: django-error-logger
Version: 1.0.1
Summary: A Django application that logs HTTP 500 errors with detailed context
Home-page: https://github.com/yourusername/django-error-logger
Author: Your Name
Author-email: Your Name <your.email@example.com>
License-Expression: AGPL-3.0
Project-URL: Homepage, https://github.com/moxgreen/django-error-logger
Project-URL: Documentation, https://github.com/moxgreen/django-error-logger
Project-URL: Repository, https://github.com/moxgreen/django-error-logger
Project-URL: Bug Tracker, https://github.com/moxgreen/django-error-logger/issues
Keywords: django,error,logging,debugging,middleware
Classifier: Development Status :: 4 - Beta
Classifier: Environment :: Web Environment
Classifier: Framework :: Django
Classifier: Framework :: Django :: 3.2
Classifier: Framework :: Django :: 4.0
Classifier: Framework :: Django :: 4.1
Classifier: Framework :: Django :: 4.2
Classifier: Framework :: Django :: 5.0
Classifier: Intended Audience :: Developers
Classifier: Operating System :: OS Independent
Classifier: Programming Language :: Python
Classifier: Programming Language :: Python :: 3
Classifier: Programming Language :: Python :: 3.8
Classifier: Programming Language :: Python :: 3.9
Classifier: Programming Language :: Python :: 3.10
Classifier: Programming Language :: Python :: 3.11
Classifier: Programming Language :: Python :: 3.12
Classifier: Programming Language :: Python :: 3.13
Classifier: Topic :: Internet :: WWW/HTTP
Classifier: Topic :: Software Development :: Libraries :: Python Modules
Requires-Python: >=3.8
License-File: LICENSE
Requires-Dist: Django>=3.2
Provides-Extra: impersonation
Requires-Dist: django-su>=1.0.0; extra == "impersonation"
Dynamic: author
Dynamic: home-page
Dynamic: license-file
Dynamic: requires-python
